{
  "namedqueries": [
    {
      "path": "jsonschema.rqg",
      "uri": "https://www.w3.org/2019/wot/json-schema#"
    },
    {
      "path": "glue.rqg",
      "uri": "https://schema.ocsf.io/1.3.0/glue"
    },
    {
      "path": "categories.rqg",
      "uri": "https://schema.ocsf.io/1.3.0/categories"
    },
    {
      "path": "attribute.rqg",
      "uri": "https://schema.ocsf.io/1.3.0/attribute"
    },
    {
      "path": "type.rqg",
      "uri": "https://schema.ocsf.io/1.3.0/type"
    },
    {
      "path": "object.rqg",
      "uri": "https://schema.ocsf.io/1.3.0/object"
    },
    {
      "path": "event.rqg",
      "uri": "https://schema.ocsf.io/1.3.0/event"
    },
    {
      "path": "events.rqg",
      "uri": "https://schema.ocsf.io/1.3.0/events"
    },
    {
      "path": "objects.rqg",
      "uri": "https://schema.ocsf.io/1.3.0/objects"
    },
    {
      "path": "dictionary.rqg",
      "uri": "https://schema.ocsf.io/1.3.0/dictionary"
    }
  ],
  "graph": "dataset/ocsf.ttl"
}
